README.rst
setup.cfg
setup.py
consulbacks3/__init__.py
consulbacks3/consulbacks3
consulbacks3/consulbacks3-configure
consulbacks3/s3upload.py
consulbacks3.egg-info/PKG-INFO
consulbacks3.egg-info/SOURCES.txt
consulbacks3.egg-info/dependency_links.txt
consulbacks3.egg-info/not-zip-safe
consulbacks3.egg-info/requires.txt
consulbacks3.egg-info/top_level.txt