Metadata-Version: 1.1
Name: consulbacks3
Version: 0.0.1.5
Summary: Backup the consul key value pair directory wise in  yml files and uploads to an s3 bucket 
Home-page: https://github.com/Ankit-Kulkarni/consulbacks3
Author: Ankit Kulkarni
Author-email: ankit.kul1890@gmail.com
License: ISC
Keywords: consul,backup,yml,key-value,boto,s3,s3bucket,bucket,cli,command
Platform: UNKNOWN
Classifier: Intended Audience :: Developers 
Classifier: Natural Language :: English
Classifier: Environment :: Console
Classifier: Topic :: Utilities
